MANIFEST.in
README.md
setup.py
sslurl/__init__.py
sslurl.egg-info/PKG-INFO
sslurl.egg-info/SOURCES.txt
sslurl.egg-info/dependency_links.txt
sslurl.egg-info/entry_points.txt
sslurl.egg-info/not-zip-safe
sslurl.egg-info/requires.txt
sslurl.egg-info/top_level.txt