Metadata-Version: 1.0
Name: sslurl
Version: 2018.8.15.1701
Summary: URL HTTP to HTTPS redirection website
Home-page: https://github.com/wdbm/sslurl
Author: Will Breaden Madden
Author-email: wbm@protonmail.ch
License: GPLv3
Platform: UNKNOWN
